{
    "respondent_id": "0000451965", 
    "institution_name": "WELLS FARGO BANK, NA", 
    "table": "4-2", 
    "type": "Disclosure", 
    "desc": "Disposition of applications for conventional home-purchase loans 1- to 4- family and manufactured home dwellings, by race, ethnicity, gender and income of applicant", 
    "year": "2013", 
    "report-date": "05/28/2015", 
    "msa": {
        "id": "11500", 
        "name": "Anniston-Oxford", 
        "state": "AL", 
        "state_name": "Alabama"
    }, 
    "races": [
        {
            "race": "American Indian/Alaska Native", 
            "dispositions": [
                {
                    "disposition": "Applications Received", 
                    "count": 0, 
                    "value": 0
                }, 
                {
                    "disposition": "Loans Originated", 
                    "count": 0, 
                    "value": 0
                }, 
                {
                    "disposition": "Apps. Approved But Not Accepted", 
                    "count": 0, 
                    "value": 0
                }, 
                {
                    "disposition": "Applications Denied", 
                    "count": 0, 
                    "value": 0
                }, 
                {
                    "disposition": "Applications Withdrawn", 
                    "count": 0, 
                    "value": 0
                }, 
                {
                    "disposition": "Files Closed For Incompleteness", 
                    "count": 0, 
                    "value": 0
                }
            ], 
            "genders": [
                {
                    "gender": "Male", 
                    "dispositions": [
                        {
                            "disposition": "Applications Received", 
                            "count": 0, 
                            "value": 0
                        }, 
                        {
                            "disposition": "Loans Originated", 
                            "count": 0, 
                            "value": 0
                        }, 
                        {
                            "disposition": "Apps. Approved But Not Accepted", 
                            "count": 0, 
                            "value": 0
                        }, 
                        {
                            "disposition": "Applications Denied", 
                            "count": 0, 
                            "value": 0
                        }, 
                        {
                            "disposition": "Applications Withdrawn", 
                            "count": 0, 
                            "value": 0
                        }, 
                        {
                            "disposition": "Files Closed For Incompleteness", 
                            "count": 0, 
                            "value": 0
                        }
                    ]
                }, 
                {
                    "gender": "Female", 
                    "dispositions": [
                        {
                            "disposition": "Applications Received", 
                            "count": 0, 
                            "value": 0
                        }, 
                        {
                            "disposition": "Loans Originated", 
                            "count": 0, 
                            "value": 0
                        }, 
                        {
                            "disposition": "Apps. Approved But Not Accepted", 
                            "count": 0, 
                            "value": 0
                        }, 
                        {
                            "disposition": "Applications Denied", 
                            "count": 0, 
                            "value": 0
                        }, 
                        {
                            "disposition": "Applications Withdrawn", 
                            "count": 0, 
                            "value": 0
                        }, 
                        {
                            "disposition": "Files Closed For Incompleteness", 
                            "count": 0, 
                            "value": 0
                        }
                    ]
                }, 
                {
                    "gender": "Joint (Male/Female)", 
                    "dispositions": [
                        {
                            "disposition": "Applications Received", 
                            "count": 0, 
                            "value": 0
                        }, 
                        {
                            "disposition": "Loans Originated", 
                            "count": 0, 
                            "value": 0
                        }, 
                        {
                            "disposition": "Apps. Approved But Not Accepted", 
                            "count": 0, 
                            "value": 0
                        }, 
                        {
                            "disposition": "Applications Denied", 
                            "count": 0, 
                            "value": 0
                        }, 
                        {
                            "disposition": "Applications Withdrawn", 
                            "count": 0, 
                            "value": 0
                        }, 
                        {
                            "disposition": "Files Closed For Incompleteness", 
                            "count": 0, 
                            "value": 0
                        }
                    ]
                }
            ]
        }, 
        {
            "race": "Asian", 
            "dispositions": [
                {
                    "disposition": "Applications Received", 
                    "count": 0, 
                    "value": 0
                }, 
                {
                    "disposition": "Loans Originated", 
                    "count": 0, 
                    "value": 0
                }, 
                {
                    "disposition": "Apps. Approved But Not Accepted", 
                    "count": 0, 
                    "value": 0
                }, 
                {
                    "disposition": "Applications Denied", 
                    "count": 0, 
                    "value": 0
                }, 
                {
                    "disposition": "Applications Withdrawn", 
                    "count": 0, 
                    "value": 0
                }, 
                {
                    "disposition": "Files Closed For Incompleteness", 
                    "count": 0, 
                    "value": 0
                }
            ], 
            "genders": [
                {
                    "gender": "Male", 
                    "dispositions": [
                        {
                            "disposition": "Applications Received", 
                            "count": 0, 
                            "value": 0
                        }, 
                        {
                            "disposition": "Loans Originated", 
                            "count": 0, 
                            "value": 0
                        }, 
                        {
                            "disposition": "Apps. Approved But Not Accepted", 
                            "count": 0, 
                            "value": 0
                        }, 
                        {
                            "disposition": "Applications Denied", 
                            "count": 0, 
                            "value": 0
                        }, 
                        {
                            "disposition": "Applications Withdrawn", 
                            "count": 0, 
                            "value": 0
                        }, 
                        {
                            "disposition": "Files Closed For Incompleteness", 
                            "count": 0, 
                            "value": 0
                        }
                    ]
                }, 
                {
                    "gender": "Female", 
                    "dispositions": [
                        {
                            "disposition": "Applications Received", 
                            "count": 0, 
                            "value": 0
                        }, 
                        {
                            "disposition": "Loans Originated", 
                            "count": 0, 
                            "value": 0
                        }, 
                        {
                            "disposition": "Apps. Approved But Not Accepted", 
                            "count": 0, 
                            "value": 0
                        }, 
                        {
                            "disposition": "Applications Denied", 
                            "count": 0, 
                            "value": 0
                        }, 
                        {
                            "disposition": "Applications Withdrawn", 
                            "count": 0, 
                            "value": 0
                        }, 
                        {
                            "disposition": "Files Closed For Incompleteness", 
                            "count": 0, 
                            "value": 0
                        }
                    ]
                }, 
                {
                    "gender": "Joint (Male/Female)", 
                    "dispositions": [
                        {
                            "disposition": "Applications Received", 
                            "count": 0, 
                            "value": 0
                        }, 
                        {
                            "disposition": "Loans Originated", 
                            "count": 0, 
                            "value": 0
                        }, 
                        {
                            "disposition": "Apps. Approved But Not Accepted", 
                            "count": 0, 
                            "value": 0
                        }, 
                        {
                            "disposition": "Applications Denied", 
                            "count": 0, 
                            "value": 0
                        }, 
                        {
                            "disposition": "Applications Withdrawn", 
                            "count": 0, 
                            "value": 0
                        }, 
                        {
                            "disposition": "Files Closed For Incompleteness", 
                            "count": 0, 
                            "value": 0
                        }
                    ]
                }
            ]
        }, 
        {
            "race": "Black or African American", 
            "dispositions": [
                {
                    "disposition": "Applications Received", 
                    "count": 1, 
                    "value": 106
                }, 
                {
                    "disposition": "Loans Originated", 
                    "count": 1, 
                    "value": 106
                }, 
                {
                    "disposition": "Apps. Approved But Not Accepted", 
                    "count": 0, 
                    "value": 0
                }, 
                {
                    "disposition": "Applications Denied", 
                    "count": 0, 
                    "value": 0
                }, 
                {
                    "disposition": "Applications Withdrawn", 
                    "count": 0, 
                    "value": 0
                }, 
                {
                    "disposition": "Files Closed For Incompleteness", 
                    "count": 0, 
                    "value": 0
                }
            ], 
            "genders": [
                {
                    "gender": "Male", 
                    "dispositions": [
                        {
                            "disposition": "Applications Received", 
                            "count": 1, 
                            "value": 106
                        }, 
                        {
                            "disposition": "Loans Originated", 
                            "count": 1, 
                            "value": 106
                        }, 
                        {
                            "disposition": "Apps. Approved But Not Accepted", 
                            "count": 0, 
                            "value": 0
                        }, 
                        {
                            "disposition": "Applications Denied", 
                            "count": 0, 
                            "value": 0
                        }, 
                        {
                            "disposition": "Applications Withdrawn", 
                            "count": 0, 
                            "value": 0
                        }, 
                        {
                            "disposition": "Files Closed For Incompleteness", 
                            "count": 0, 
                            "value": 0
                        }
                    ]
                }, 
                {
                    "gender": "Female", 
                    "dispositions": [
                        {
                            "disposition": "Applications Received", 
                            "count": 0, 
                            "value": 0
                        }, 
                        {
                            "disposition": "Loans Originated", 
                            "count": 0, 
                            "value": 0
                        }, 
                        {
                            "disposition": "Apps. Approved But Not Accepted", 
                            "count": 0, 
                            "value": 0
                        }, 
                        {
                            "disposition": "Applications Denied", 
                            "count": 0, 
                            "value": 0
                        }, 
                        {
                            "disposition": "Applications Withdrawn", 
                            "count": 0, 
                            "value": 0
                        }, 
                        {
                            "disposition": "Files Closed For Incompleteness", 
                            "count": 0, 
                            "value": 0
                        }
                    ]
                }, 
                {
                    "gender": "Joint (Male/Female)", 
                    "dispositions": [
                        {
                            "disposition": "Applications Received", 
                            "count": 0, 
                            "value": 0
                        }, 
                        {
                            "disposition": "Loans Originated", 
                            "count": 0, 
                            "value": 0
                        }, 
                        {
                            "disposition": "Apps. Approved But Not Accepted", 
                            "count": 0, 
                            "value": 0
                        }, 
                        {
                            "disposition": "Applications Denied", 
                            "count": 0, 
                            "value": 0
                        }, 
                        {
                            "disposition": "Applications Withdrawn", 
                            "count": 0, 
                            "value": 0
                        }, 
                        {
                            "disposition": "Files Closed For Incompleteness", 
                            "count": 0, 
                            "value": 0
                        }
                    ]
                }
            ]
        }, 
        {
            "race": "Native Hawaiian or Other Pacific Islander", 
            "dispositions": [
                {
                    "disposition": "Applications Received", 
                    "count": 1, 
                    "value": 259
                }, 
                {
                    "disposition": "Loans Originated", 
                    "count": 1, 
                    "value": 259
                }, 
                {
                    "disposition": "Apps. Approved But Not Accepted", 
                    "count": 0, 
                    "value": 0
                }, 
                {
                    "disposition": "Applications Denied", 
                    "count": 0, 
                    "value": 0
                }, 
                {
                    "disposition": "Applications Withdrawn", 
                    "count": 0, 
                    "value": 0
                }, 
                {
                    "disposition": "Files Closed For Incompleteness", 
                    "count": 0, 
                    "value": 0
                }
            ], 
            "genders": [
                {
                    "gender": "Male", 
                    "dispositions": [
                        {
                            "disposition": "Applications Received", 
                            "count": 1, 
                            "value": 259
                        }, 
                        {
                            "disposition": "Loans Originated", 
                            "count": 1, 
                            "value": 259
                        }, 
                        {
                            "disposition": "Apps. Approved But Not Accepted", 
                            "count": 0, 
                            "value": 0
                        }, 
                        {
                            "disposition": "Applications Denied", 
                            "count": 0, 
                            "value": 0
                        }, 
                        {
                            "disposition": "Applications Withdrawn", 
                            "count": 0, 
                            "value": 0
                        }, 
                        {
                            "disposition": "Files Closed For Incompleteness", 
                            "count": 0, 
                            "value": 0
                        }
                    ]
                }, 
                {
                    "gender": "Female", 
                    "dispositions": [
                        {
                            "disposition": "Applications Received", 
                            "count": 0, 
                            "value": 0
                        }, 
                        {
                            "disposition": "Loans Originated", 
                            "count": 0, 
                            "value": 0
                        }, 
                        {
                            "disposition": "Apps. Approved But Not Accepted", 
                            "count": 0, 
                            "value": 0
                        }, 
                        {
                            "disposition": "Applications Denied", 
                            "count": 0, 
                            "value": 0
                        }, 
                        {
                            "disposition": "Applications Withdrawn", 
                            "count": 0, 
                            "value": 0
                        }, 
                        {
                            "disposition": "Files Closed For Incompleteness", 
                            "count": 0, 
                            "value": 0
                        }
                    ]
                }, 
                {
                    "gender": "Joint (Male/Female)", 
                    "dispositions": [
                        {
                            "disposition": "Applications Received", 
                            "count": 0, 
                            "value": 0
                        }, 
                        {
                            "disposition": "Loans Originated", 
                            "count": 0, 
                            "value": 0
                        }, 
                        {
                            "disposition": "Apps. Approved But Not Accepted", 
                            "count": 0, 
                            "value": 0
                        }, 
                        {
                            "disposition": "Applications Denied", 
                            "count": 0, 
                            "value": 0
                        }, 
                        {
                            "disposition": "Applications Withdrawn", 
                            "count": 0, 
                            "value": 0
                        }, 
                        {
                            "disposition": "Files Closed For Incompleteness", 
                            "count": 0, 
                            "value": 0
                        }
                    ]
                }
            ]
        }, 
        {
            "race": "White", 
            "dispositions": [
                {
                    "disposition": "Applications Received", 
                    "count": 15, 
                    "value": 1682
                }, 
                {
                    "disposition": "Loans Originated", 
                    "count": 10, 
                    "value": 1444
                }, 
                {
                    "disposition": "Apps. Approved But Not Accepted", 
                    "count": 0, 
                    "value": 0
                }, 
                {
                    "disposition": "Applications Denied", 
                    "count": 3, 
                    "value": 133
                }, 
                {
                    "disposition": "Applications Withdrawn", 
                    "count": 2, 
                    "value": 105
                }, 
                {
                    "disposition": "Files Closed For Incompleteness", 
                    "count": 0, 
                    "value": 0
                }
            ], 
            "genders": [
                {
                    "gender": "Male", 
                    "dispositions": [
                        {
                            "disposition": "Applications Received", 
                            "count": 8, 
                            "value": 652
                        }, 
                        {
                            "disposition": "Loans Originated", 
                            "count": 5, 
                            "value": 525
                        }, 
                        {
                            "disposition": "Apps. Approved But Not Accepted", 
                            "count": 0, 
                            "value": 0
                        }, 
                        {
                            "disposition": "Applications Denied", 
                            "count": 2, 
                            "value": 72
                        }, 
                        {
                            "disposition": "Applications Withdrawn", 
                            "count": 1, 
                            "value": 55
                        }, 
                        {
                            "disposition": "Files Closed For Incompleteness", 
                            "count": 0, 
                            "value": 0
                        }
                    ]
                }, 
                {
                    "gender": "Female", 
                    "dispositions": [
                        {
                            "disposition": "Applications Received", 
                            "count": 1, 
                            "value": 50
                        }, 
                        {
                            "disposition": "Loans Originated", 
                            "count": 0, 
                            "value": 0
                        }, 
                        {
                            "disposition": "Apps. Approved But Not Accepted", 
                            "count": 0, 
                            "value": 0
                        }, 
                        {
                            "disposition": "Applications Denied", 
                            "count": 0, 
                            "value": 0
                        }, 
                        {
                            "disposition": "Applications Withdrawn", 
                            "count": 1, 
                            "value": 50
                        }, 
                        {
                            "disposition": "Files Closed For Incompleteness", 
                            "count": 0, 
                            "value": 0
                        }
                    ]
                }, 
                {
                    "gender": "Joint (Male/Female)", 
                    "dispositions": [
                        {
                            "disposition": "Applications Received", 
                            "count": 6, 
                            "value": 980
                        }, 
                        {
                            "disposition": "Loans Originated", 
                            "count": 5, 
                            "value": 919
                        }, 
                        {
                            "disposition": "Apps. Approved But Not Accepted", 
                            "count": 0, 
                            "value": 0
                        }, 
                        {
                            "disposition": "Applications Denied", 
                            "count": 1, 
                            "value": 61
                        }, 
                        {
                            "disposition": "Applications Withdrawn", 
                            "count": 0, 
                            "value": 0
                        }, 
                        {
                            "disposition": "Files Closed For Incompleteness", 
                            "count": 0, 
                            "value": 0
                        }
                    ]
                }
            ]
        }, 
        {
            "race": "2 or more minority races", 
            "dispositions": [
                {
                    "disposition": "Applications Received", 
                    "count": 0, 
                    "value": 0
                }, 
                {
                    "disposition": "Loans Originated", 
                    "count": 0, 
                    "value": 0
                }, 
                {
                    "disposition": "Apps. Approved But Not Accepted", 
                    "count": 0, 
                    "value": 0
                }, 
                {
                    "disposition": "Applications Denied", 
                    "count": 0, 
                    "value": 0
                }, 
                {
                    "disposition": "Applications Withdrawn", 
                    "count": 0, 
                    "value": 0
                }, 
                {
                    "disposition": "Files Closed For Incompleteness", 
                    "count": 0, 
                    "value": 0
                }
            ], 
            "genders": [
                {
                    "gender": "Male", 
                    "dispositions": [
                        {
                            "disposition": "Applications Received", 
                            "count": 0, 
                            "value": 0
                        }, 
                        {
                            "disposition": "Loans Originated", 
                            "count": 0, 
                            "value": 0
                        }, 
                        {
                            "disposition": "Apps. Approved But Not Accepted", 
                            "count": 0, 
                            "value": 0
                        }, 
                        {
                            "disposition": "Applications Denied", 
                            "count": 0, 
                            "value": 0
                        }, 
                        {
                            "disposition": "Applications Withdrawn", 
                            "count": 0, 
                            "value": 0
                        }, 
                        {
                            "disposition": "Files Closed For Incompleteness", 
                            "count": 0, 
                            "value": 0
                        }
                    ]
                }, 
                {
                    "gender": "Female", 
                    "dispositions": [
                        {
                            "disposition": "Applications Received", 
                            "count": 0, 
                            "value": 0
                        }, 
                        {
                            "disposition": "Loans Originated", 
                            "count": 0, 
                            "value": 0
                        }, 
                        {
                            "disposition": "Apps. Approved But Not Accepted", 
                            "count": 0, 
                            "value": 0
                        }, 
                        {
                            "disposition": "Applications Denied", 
                            "count": 0, 
                            "value": 0
                        }, 
                        {
                            "disposition": "Applications Withdrawn", 
                            "count": 0, 
                            "value": 0
                        }, 
                        {
                            "disposition": "Files Closed For Incompleteness", 
                            "count": 0, 
                            "value": 0
                        }
                    ]
                }, 
                {
                    "gender": "Joint (Male/Female)", 
                    "dispositions": [
                        {
                            "disposition": "Applications Received", 
                            "count": 0, 
                            "value": 0
                        }, 
                        {
                            "disposition": "Loans Originated", 
                            "count": 0, 
                            "value": 0
                        }, 
                        {
                            "disposition": "Apps. Approved But Not Accepted", 
                            "count": 0, 
                            "value": 0
                        }, 
                        {
                            "disposition": "Applications Denied", 
                            "count": 0, 
                            "value": 0
                        }, 
                        {
                            "disposition": "Applications Withdrawn", 
                            "count": 0, 
                            "value": 0
                        }, 
                        {
                            "disposition": "Files Closed For Incompleteness", 
                            "count": 0, 
                            "value": 0
                        }
                    ]
                }
            ]
        }, 
        {
            "race": "Joint (White/Minority Race)", 
            "dispositions": [
                {
                    "disposition": "Applications Received", 
                    "count": 1, 
                    "value": 220
                }, 
                {
                    "disposition": "Loans Originated", 
                    "count": 1, 
                    "value": 220
                }, 
                {
                    "disposition": "Apps. Approved But Not Accepted", 
                    "count": 0, 
                    "value": 0
                }, 
                {
                    "disposition": "Applications Denied", 
                    "count": 0, 
                    "value": 0
                }, 
                {
                    "disposition": "Applications Withdrawn", 
                    "count": 0, 
                    "value": 0
                }, 
                {
                    "disposition": "Files Closed For Incompleteness", 
                    "count": 0, 
                    "value": 0
                }
            ], 
            "genders": [
                {
                    "gender": "Male", 
                    "dispositions": [
                        {
                            "disposition": "Applications Received", 
                            "count": 0, 
                            "value": 0
                        }, 
                        {
                            "disposition": "Loans Originated", 
                            "count": 0, 
                            "value": 0
                        }, 
                        {
                            "disposition": "Apps. Approved But Not Accepted", 
                            "count": 0, 
                            "value": 0
                        }, 
                        {
                            "disposition": "Applications Denied", 
                            "count": 0, 
                            "value": 0
                        }, 
                        {
                            "disposition": "Applications Withdrawn", 
                            "count": 0, 
                            "value": 0
                        }, 
                        {
                            "disposition": "Files Closed For Incompleteness", 
                            "count": 0, 
                            "value": 0
                        }
                    ]
                }, 
                {
                    "gender": "Female", 
                    "dispositions": [
                        {
                            "disposition": "Applications Received", 
                            "count": 0, 
                            "value": 0
                        }, 
                        {
                            "disposition": "Loans Originated", 
                            "count": 0, 
                            "value": 0
                        }, 
                        {
                            "disposition": "Apps. Approved But Not Accepted", 
                            "count": 0, 
                            "value": 0
                        }, 
                        {
                            "disposition": "Applications Denied", 
                            "count": 0, 
                            "value": 0
                        }, 
                        {
                            "disposition": "Applications Withdrawn", 
                            "count": 0, 
                            "value": 0
                        }, 
                        {
                            "disposition": "Files Closed For Incompleteness", 
                            "count": 0, 
                            "value": 0
                        }
                    ]
                }, 
                {
                    "gender": "Joint (Male/Female)", 
                    "dispositions": [
                        {
                            "disposition": "Applications Received", 
                            "count": 1, 
                            "value": 220
                        }, 
                        {
                            "disposition": "Loans Originated", 
                            "count": 1, 
                            "value": 220
                        }, 
                        {
                            "disposition": "Apps. Approved But Not Accepted", 
                            "count": 0, 
                            "value": 0
                        }, 
                        {
                            "disposition": "Applications Denied", 
                            "count": 0, 
                            "value": 0
                        }, 
                        {
                            "disposition": "Applications Withdrawn", 
                            "count": 0, 
                            "value": 0
                        }, 
                        {
                            "disposition": "Files Closed For Incompleteness", 
                            "count": 0, 
                            "value": 0
                        }
                    ]
                }
            ]
        }, 
        {
            "race": "Race Not Available", 
            "dispositions": [
                {
                    "disposition": "Applications Received", 
                    "count": 4, 
                    "value": 275
                }, 
                {
                    "disposition": "Loans Originated", 
                    "count": 1, 
                    "value": 54
                }, 
                {
                    "disposition": "Apps. Approved But Not Accepted", 
                    "count": 0, 
                    "value": 0
                }, 
                {
                    "disposition": "Applications Denied", 
                    "count": 3, 
                    "value": 221
                }, 
                {
                    "disposition": "Applications Withdrawn", 
                    "count": 0, 
                    "value": 0
                }, 
                {
                    "disposition": "Files Closed For Incompleteness", 
                    "count": 0, 
                    "value": 0
                }
            ], 
            "genders": [
                {
                    "gender": "Male", 
                    "dispositions": [
                        {
                            "disposition": "Applications Received", 
                            "count": 2, 
                            "value": 191
                        }, 
                        {
                            "disposition": "Loans Originated", 
                            "count": 0, 
                            "value": 0
                        }, 
                        {
                            "disposition": "Apps. Approved But Not Accepted", 
                            "count": 0, 
                            "value": 0
                        }, 
                        {
                            "disposition": "Applications Denied", 
                            "count": 2, 
                            "value": 191
                        }, 
                        {
                            "disposition": "Applications Withdrawn", 
                            "count": 0, 
                            "value": 0
                        }, 
                        {
                            "disposition": "Files Closed For Incompleteness", 
                            "count": 0, 
                            "value": 0
                        }
                    ]
                }, 
                {
                    "gender": "Female", 
                    "dispositions": [
                        {
                            "disposition": "Applications Received", 
                            "count": 0, 
                            "value": 0
                        }, 
                        {
                            "disposition": "Loans Originated", 
                            "count": 0, 
                            "value": 0
                        }, 
                        {
                            "disposition": "Apps. Approved But Not Accepted", 
                            "count": 0, 
                            "value": 0
                        }, 
                        {
                            "disposition": "Applications Denied", 
                            "count": 0, 
                            "value": 0
                        }, 
                        {
                            "disposition": "Applications Withdrawn", 
                            "count": 0, 
                            "value": 0
                        }, 
                        {
                            "disposition": "Files Closed For Incompleteness", 
                            "count": 0, 
                            "value": 0
                        }
                    ]
                }, 
                {
                    "gender": "Joint (Male/Female)", 
                    "dispositions": [
                        {
                            "disposition": "Applications Received", 
                            "count": 0, 
                            "value": 0
                        }, 
                        {
                            "disposition": "Loans Originated", 
                            "count": 0, 
                            "value": 0
                        }, 
                        {
                            "disposition": "Apps. Approved But Not Accepted", 
                            "count": 0, 
                            "value": 0
                        }, 
                        {
                            "disposition": "Applications Denied", 
                            "count": 0, 
                            "value": 0
                        }, 
                        {
                            "disposition": "Applications Withdrawn", 
                            "count": 0, 
                            "value": 0
                        }, 
                        {
                            "disposition": "Files Closed For Incompleteness", 
                            "count": 0, 
                            "value": 0
                        }
                    ]
                }
            ]
        }
    ], 
    "ethnicities": [
        {
            "ethnicity": "Hispanic or Latino", 
            "dispositions": [
                {
                    "disposition": "Applications Received", 
                    "count": 1, 
                    "value": 93
                }, 
                {
                    "disposition": "Loans Originated", 
                    "count": 0, 
                    "value": 0
                }, 
                {
                    "disposition": "Apps. Approved But Not Accepted", 
                    "count": 0, 
                    "value": 0
                }, 
                {
                    "disposition": "Applications Denied", 
                    "count": 1, 
                    "value": 93
                }, 
                {
                    "disposition": "Applications Withdrawn", 
                    "count": 0, 
                    "value": 0
                }, 
                {
                    "disposition": "Files Closed For Incompleteness", 
                    "count": 0, 
                    "value": 0
                }
            ], 
            "genders": [
                {
                    "gender": "Male", 
                    "dispositions": [
                        {
                            "disposition": "Applications Received", 
                            "count": 1, 
                            "value": 93
                        }, 
                        {
                            "disposition": "Loans Originated", 
                            "count": 0, 
                            "value": 0
                        }, 
                        {
                            "disposition": "Apps. Approved But Not Accepted", 
                            "count": 0, 
                            "value": 0
                        }, 
                        {
                            "disposition": "Applications Denied", 
                            "count": 1, 
                            "value": 93
                        }, 
                        {
                            "disposition": "Applications Withdrawn", 
                            "count": 0, 
                            "value": 0
                        }, 
                        {
                            "disposition": "Files Closed For Incompleteness", 
                            "count": 0, 
                            "value": 0
                        }
                    ]
                }, 
                {
                    "gender": "Female", 
                    "dispositions": [
                        {
                            "disposition": "Applications Received", 
                            "count": 0, 
                            "value": 0
                        }, 
                        {
                            "disposition": "Loans Originated", 
                            "count": 0, 
                            "value": 0
                        }, 
                        {
                            "disposition": "Apps. Approved But Not Accepted", 
                            "count": 0, 
                            "value": 0
                        }, 
                        {
                            "disposition": "Applications Denied", 
                            "count": 0, 
                            "value": 0
                        }, 
                        {
                            "disposition": "Applications Withdrawn", 
                            "count": 0, 
                            "value": 0
                        }, 
                        {
                            "disposition": "Files Closed For Incompleteness", 
                            "count": 0, 
                            "value": 0
                        }
                    ]
                }, 
                {
                    "gender": "Joint (Male/Female)", 
                    "dispositions": [
                        {
                            "disposition": "Applications Received", 
                            "count": 0, 
                            "value": 0
                        }, 
                        {
                            "disposition": "Loans Originated", 
                            "count": 0, 
                            "value": 0
                        }, 
                        {
                            "disposition": "Apps. Approved But Not Accepted", 
                            "count": 0, 
                            "value": 0
                        }, 
                        {
                            "disposition": "Applications Denied", 
                            "count": 0, 
                            "value": 0
                        }, 
                        {
                            "disposition": "Applications Withdrawn", 
                            "count": 0, 
                            "value": 0
                        }, 
                        {
                            "disposition": "Files Closed For Incompleteness", 
                            "count": 0, 
                            "value": 0
                        }
                    ]
                }
            ]
        }, 
        {
            "ethnicity": "Not Hispanic or Latino", 
            "dispositions": [
                {
                    "disposition": "Applications Received", 
                    "count": 19, 
                    "value": 2365
                }, 
                {
                    "disposition": "Loans Originated", 
                    "count": 13, 
                    "value": 2029
                }, 
                {
                    "disposition": "Apps. Approved But Not Accepted", 
                    "count": 0, 
                    "value": 0
                }, 
                {
                    "disposition": "Applications Denied", 
                    "count": 4, 
                    "value": 231
                }, 
                {
                    "disposition": "Applications Withdrawn", 
                    "count": 2, 
                    "value": 105
                }, 
                {
                    "disposition": "Files Closed For Incompleteness", 
                    "count": 0, 
                    "value": 0
                }
            ], 
            "genders": [
                {
                    "gender": "Male", 
                    "dispositions": [
                        {
                            "disposition": "Applications Received", 
                            "count": 11, 
                            "value": 1115
                        }, 
                        {
                            "disposition": "Loans Originated", 
                            "count": 7, 
                            "value": 890
                        }, 
                        {
                            "disposition": "Apps. Approved But Not Accepted", 
                            "count": 0, 
                            "value": 0
                        }, 
                        {
                            "disposition": "Applications Denied", 
                            "count": 3, 
                            "value": 170
                        }, 
                        {
                            "disposition": "Applications Withdrawn", 
                            "count": 1, 
                            "value": 55
                        }, 
                        {
                            "disposition": "Files Closed For Incompleteness", 
                            "count": 0, 
                            "value": 0
                        }
                    ]
                }, 
                {
                    "gender": "Female", 
                    "dispositions": [
                        {
                            "disposition": "Applications Received", 
                            "count": 1, 
                            "value": 50
                        }, 
                        {
                            "disposition": "Loans Originated", 
                            "count": 0, 
                            "value": 0
                        }, 
                        {
                            "disposition": "Apps. Approved But Not Accepted", 
                            "count": 0, 
                            "value": 0
                        }, 
                        {
                            "disposition": "Applications Denied", 
                            "count": 0, 
                            "value": 0
                        }, 
                        {
                            "disposition": "Applications Withdrawn", 
                            "count": 1, 
                            "value": 50
                        }, 
                        {
                            "disposition": "Files Closed For Incompleteness", 
                            "count": 0, 
                            "value": 0
                        }
                    ]
                }, 
                {
                    "gender": "Joint (Male/Female)", 
                    "dispositions": [
                        {
                            "disposition": "Applications Received", 
                            "count": 7, 
                            "value": 1200
                        }, 
                        {
                            "disposition": "Loans Originated", 
                            "count": 6, 
                            "value": 1139
                        }, 
                        {
                            "disposition": "Apps. Approved But Not Accepted", 
                            "count": 0, 
                            "value": 0
                        }, 
                        {
                            "disposition": "Applications Denied", 
                            "count": 1, 
                            "value": 61
                        }, 
                        {
                            "disposition": "Applications Withdrawn", 
                            "count": 0, 
                            "value": 0
                        }, 
                        {
                            "disposition": "Files Closed For Incompleteness", 
                            "count": 0, 
                            "value": 0
                        }
                    ]
                }
            ]
        }, 
        {
            "ethnicity": "Joint (Hispanic or Latino/Not Hispanic or Latino)", 
            "dispositions": [
                {
                    "disposition": "Applications Received", 
                    "count": 0, 
                    "value": 0
                }, 
                {
                    "disposition": "Loans Originated", 
                    "count": 0, 
                    "value": 0
                }, 
                {
                    "disposition": "Apps. Approved But Not Accepted", 
                    "count": 0, 
                    "value": 0
                }, 
                {
                    "disposition": "Applications Denied", 
                    "count": 0, 
                    "value": 0
                }, 
                {
                    "disposition": "Applications Withdrawn", 
                    "count": 0, 
                    "value": 0
                }, 
                {
                    "disposition": "Files Closed For Incompleteness", 
                    "count": 0, 
                    "value": 0
                }
            ], 
            "genders": [
                {
                    "gender": "Male", 
                    "dispositions": [
                        {
                            "disposition": "Applications Received", 
                            "count": 0, 
                            "value": 0
                        }, 
                        {
                            "disposition": "Loans Originated", 
                            "count": 0, 
                            "value": 0
                        }, 
                        {
                            "disposition": "Apps. Approved But Not Accepted", 
                            "count": 0, 
                            "value": 0
                        }, 
                        {
                            "disposition": "Applications Denied", 
                            "count": 0, 
                            "value": 0
                        }, 
                        {
                            "disposition": "Applications Withdrawn", 
                            "count": 0, 
                            "value": 0
                        }, 
                        {
                            "disposition": "Files Closed For Incompleteness", 
                            "count": 0, 
                            "value": 0
                        }
                    ]
                }, 
                {
                    "gender": "Female", 
                    "dispositions": [
                        {
                            "disposition": "Applications Received", 
                            "count": 0, 
                            "value": 0
                        }, 
                        {
                            "disposition": "Loans Originated", 
                            "count": 0, 
                            "value": 0
                        }, 
                        {
                            "disposition": "Apps. Approved But Not Accepted", 
                            "count": 0, 
                            "value": 0
                        }, 
                        {
                            "disposition": "Applications Denied", 
                            "count": 0, 
                            "value": 0
                        }, 
                        {
                            "disposition": "Applications Withdrawn", 
                            "count": 0, 
                            "value": 0
                        }, 
                        {
                            "disposition": "Files Closed For Incompleteness", 
                            "count": 0, 
                            "value": 0
                        }
                    ]
                }, 
                {
                    "gender": "Joint (Male/Female)", 
                    "dispositions": [
                        {
                            "disposition": "Applications Received", 
                            "count": 0, 
                            "value": 0
                        }, 
                        {
                            "disposition": "Loans Originated", 
                            "count": 0, 
                            "value": 0
                        }, 
                        {
                            "disposition": "Apps. Approved But Not Accepted", 
                            "count": 0, 
                            "value": 0
                        }, 
                        {
                            "disposition": "Applications Denied", 
                            "count": 0, 
                            "value": 0
                        }, 
                        {
                            "disposition": "Applications Withdrawn", 
                            "count": 0, 
                            "value": 0
                        }, 
                        {
                            "disposition": "Files Closed For Incompleteness", 
                            "count": 0, 
                            "value": 0
                        }
                    ]
                }
            ]
        }, 
        {
            "ethnicity": "Ethnicity Not Available", 
            "dispositions": [
                {
                    "disposition": "Applications Received", 
                    "count": 2, 
                    "value": 84
                }, 
                {
                    "disposition": "Loans Originated", 
                    "count": 1, 
                    "value": 54
                }, 
                {
                    "disposition": "Apps. Approved But Not Accepted", 
                    "count": 0, 
                    "value": 0
                }, 
                {
                    "disposition": "Applications Denied", 
                    "count": 1, 
                    "value": 30
                }, 
                {
                    "disposition": "Applications Withdrawn", 
                    "count": 0, 
                    "value": 0
                }, 
                {
                    "disposition": "Files Closed For Incompleteness", 
                    "count": 0, 
                    "value": 0
                }
            ], 
            "genders": [
                {
                    "gender": "Male", 
                    "dispositions": [
                        {
                            "disposition": "Applications Received", 
                            "count": 0, 
                            "value": 0
                        }, 
                        {
                            "disposition": "Loans Originated", 
                            "count": 0, 
                            "value": 0
                        }, 
                        {
                            "disposition": "Apps. Approved But Not Accepted", 
                            "count": 0, 
                            "value": 0
                        }, 
                        {
                            "disposition": "Applications Denied", 
                            "count": 0, 
                            "value": 0
                        }, 
                        {
                            "disposition": "Applications Withdrawn", 
                            "count": 0, 
                            "value": 0
                        }, 
                        {
                            "disposition": "Files Closed For Incompleteness", 
                            "count": 0, 
                            "value": 0
                        }
                    ]
                }, 
                {
                    "gender": "Female", 
                    "dispositions": [
                        {
                            "disposition": "Applications Received", 
                            "count": 0, 
                            "value": 0
                        }, 
                        {
                            "disposition": "Loans Originated", 
                            "count": 0, 
                            "value": 0
                        }, 
                        {
                            "disposition": "Apps. Approved But Not Accepted", 
                            "count": 0, 
                            "value": 0
                        }, 
                        {
                            "disposition": "Applications Denied", 
                            "count": 0, 
                            "value": 0
                        }, 
                        {
                            "disposition": "Applications Withdrawn", 
                            "count": 0, 
                            "value": 0
                        }, 
                        {
                            "disposition": "Files Closed For Incompleteness", 
                            "count": 0, 
                            "value": 0
                        }
                    ]
                }, 
                {
                    "gender": "Joint (Male/Female)", 
                    "dispositions": [
                        {
                            "disposition": "Applications Received", 
                            "count": 0, 
                            "value": 0
                        }, 
                        {
                            "disposition": "Loans Originated", 
                            "count": 0, 
                            "value": 0
                        }, 
                        {
                            "disposition": "Apps. Approved But Not Accepted", 
                            "count": 0, 
                            "value": 0
                        }, 
                        {
                            "disposition": "Applications Denied", 
                            "count": 0, 
                            "value": 0
                        }, 
                        {
                            "disposition": "Applications Withdrawn", 
                            "count": 0, 
                            "value": 0
                        }, 
                        {
                            "disposition": "Files Closed For Incompleteness", 
                            "count": 0, 
                            "value": 0
                        }
                    ]
                }
            ]
        }
    ], 
    "minoritystatuses": [
        {
            "minoritystatus": "White Non-Hispanic", 
            "dispositions": [
                {
                    "disposition": "Applications Received", 
                    "count": 15, 
                    "value": 1682
                }, 
                {
                    "disposition": "Loans Originated", 
                    "count": 10, 
                    "value": 1444
                }, 
                {
                    "disposition": "Apps. Approved But Not Accepted", 
                    "count": 0, 
                    "value": 0
                }, 
                {
                    "disposition": "Applications Denied", 
                    "count": 3, 
                    "value": 133
                }, 
                {
                    "disposition": "Applications Withdrawn", 
                    "count": 2, 
                    "value": 105
                }, 
                {
                    "disposition": "Files Closed For Incompleteness", 
                    "count": 0, 
                    "value": 0
                }
            ], 
            "genders": [
                {
                    "gender": "Male", 
                    "dispositions": [
                        {
                            "disposition": "Applications Received", 
                            "count": 8, 
                            "value": 652
                        }, 
                        {
                            "disposition": "Loans Originated", 
                            "count": 5, 
                            "value": 525
                        }, 
                        {
                            "disposition": "Apps. Approved But Not Accepted", 
                            "count": 0, 
                            "value": 0
                        }, 
                        {
                            "disposition": "Applications Denied", 
                            "count": 2, 
                            "value": 72
                        }, 
                        {
                            "disposition": "Applications Withdrawn", 
                            "count": 1, 
                            "value": 55
                        }, 
                        {
                            "disposition": "Files Closed For Incompleteness", 
                            "count": 0, 
                            "value": 0
                        }
                    ]
                }, 
                {
                    "gender": "Female", 
                    "dispositions": [
                        {
                            "disposition": "Applications Received", 
                            "count": 1, 
                            "value": 50
                        }, 
                        {
                            "disposition": "Loans Originated", 
                            "count": 0, 
                            "value": 0
                        }, 
                        {
                            "disposition": "Apps. Approved But Not Accepted", 
                            "count": 0, 
                            "value": 0
                        }, 
                        {
                            "disposition": "Applications Denied", 
                            "count": 0, 
                            "value": 0
                        }, 
                        {
                            "disposition": "Applications Withdrawn", 
                            "count": 1, 
                            "value": 50
                        }, 
                        {
                            "disposition": "Files Closed For Incompleteness", 
                            "count": 0, 
                            "value": 0
                        }
                    ]
                }, 
                {
                    "gender": "Joint (Male/Female)", 
                    "dispositions": [
                        {
                            "disposition": "Applications Received", 
                            "count": 6, 
                            "value": 980
                        }, 
                        {
                            "disposition": "Loans Originated", 
                            "count": 5, 
                            "value": 919
                        }, 
                        {
                            "disposition": "Apps. Approved But Not Accepted", 
                            "count": 0, 
                            "value": 0
                        }, 
                        {
                            "disposition": "Applications Denied", 
                            "count": 1, 
                            "value": 61
                        }, 
                        {
                            "disposition": "Applications Withdrawn", 
                            "count": 0, 
                            "value": 0
                        }, 
                        {
                            "disposition": "Files Closed For Incompleteness", 
                            "count": 0, 
                            "value": 0
                        }
                    ]
                }
            ]
        }, 
        {
            "minoritystatus": "Others, Including Hispanic", 
            "dispositions": [
                {
                    "disposition": "Applications Received", 
                    "count": 4, 
                    "value": 678
                }, 
                {
                    "disposition": "Loans Originated", 
                    "count": 3, 
                    "value": 585
                }, 
                {
                    "disposition": "Apps. Approved But Not Accepted", 
                    "count": 0, 
                    "value": 0
                }, 
                {
                    "disposition": "Applications Denied", 
                    "count": 1, 
                    "value": 93
                }, 
                {
                    "disposition": "Applications Withdrawn", 
                    "count": 0, 
                    "value": 0
                }, 
                {
                    "disposition": "Files Closed For Incompleteness", 
                    "count": 0, 
                    "value": 0
                }
            ], 
            "genders": [
                {
                    "gender": "Male", 
                    "dispositions": [
                        {
                            "disposition": "Applications Received", 
                            "count": 3, 
                            "value": 458
                        }, 
                        {
                            "disposition": "Loans Originated", 
                            "count": 2, 
                            "value": 365
                        }, 
                        {
                            "disposition": "Apps. Approved But Not Accepted", 
                            "count": 0, 
                            "value": 0
                        }, 
                        {
                            "disposition": "Applications Denied", 
                            "count": 1, 
                            "value": 93
                        }, 
                        {
                            "disposition": "Applications Withdrawn", 
                            "count": 0, 
                            "value": 0
                        }, 
                        {
                            "disposition": "Files Closed For Incompleteness", 
                            "count": 0, 
                            "value": 0
                        }
                    ]
                }, 
                {
                    "gender": "Female", 
                    "dispositions": [
                        {
                            "disposition": "Applications Received", 
                            "count": 0, 
                            "value": 0
                        }, 
                        {
                            "disposition": "Loans Originated", 
                            "count": 0, 
                            "value": 0
                        }, 
                        {
                            "disposition": "Apps. Approved But Not Accepted", 
                            "count": 0, 
                            "value": 0
                        }, 
                        {
                            "disposition": "Applications Denied", 
                            "count": 0, 
                            "value": 0
                        }, 
                        {
                            "disposition": "Applications Withdrawn", 
                            "count": 0, 
                            "value": 0
                        }, 
                        {
                            "disposition": "Files Closed For Incompleteness", 
                            "count": 0, 
                            "value": 0
                        }
                    ]
                }, 
                {
                    "gender": "Joint (Male/Female)", 
                    "dispositions": [
                        {
                            "disposition": "Applications Received", 
                            "count": 1, 
                            "value": 220
                        }, 
                        {
                            "disposition": "Loans Originated", 
                            "count": 1, 
                            "value": 220
                        }, 
                        {
                            "disposition": "Apps. Approved But Not Accepted", 
                            "count": 0, 
                            "value": 0
                        }, 
                        {
                            "disposition": "Applications Denied", 
                            "count": 0, 
                            "value": 0
                        }, 
                        {
                            "disposition": "Applications Withdrawn", 
                            "count": 0, 
                            "value": 0
                        }, 
                        {
                            "disposition": "Files Closed For Incompleteness", 
                            "count": 0, 
                            "value": 0
                        }
                    ]
                }
            ]
        }
    ], 
    "incomes": [
        {
            "income": "Less than 50% of MSA/MD median", 
            "dispositions": [
                {
                    "disposition": "Applications Received", 
                    "count": 1, 
                    "value": 30
                }, 
                {
                    "disposition": "Loans Originated", 
                    "count": 0, 
                    "value": 0
                }, 
                {
                    "disposition": "Apps. Approved But Not Accepted", 
                    "count": 0, 
                    "value": 0
                }, 
                {
                    "disposition": "Applications Denied", 
                    "count": 1, 
                    "value": 30
                }, 
                {
                    "disposition": "Applications Withdrawn", 
                    "count": 0, 
                    "value": 0
                }, 
                {
                    "disposition": "Files Closed For Incompleteness", 
                    "count": 0, 
                    "value": 0
                }
            ]
        }, 
        {
            "income": "50-79% of MSA/MD median", 
            "dispositions": [
                {
                    "disposition": "Applications Received", 
                    "count": 4, 
                    "value": 203
                }, 
                {
                    "disposition": "Loans Originated", 
                    "count": 1, 
                    "value": 54
                }, 
                {
                    "disposition": "Apps. Approved But Not Accepted", 
                    "count": 0, 
                    "value": 0
                }, 
                {
                    "disposition": "Applications Denied", 
                    "count": 2, 
                    "value": 94
                }, 
                {
                    "disposition": "Applications Withdrawn", 
                    "count": 1, 
                    "value": 55
                }, 
                {
                    "disposition": "Files Closed For Incompleteness", 
                    "count": 0, 
                    "value": 0
                }
            ]
        }, 
        {
            "income": "80-99% of MSA/MD median", 
            "dispositions": [
                {
                    "disposition": "Applications Received", 
                    "count": 1, 
                    "value": 93
                }, 
                {
                    "disposition": "Loans Originated", 
                    "count": 0, 
                    "value": 0
                }, 
                {
                    "disposition": "Apps. Approved But Not Accepted", 
                    "count": 0, 
                    "value": 0
                }, 
                {
                    "disposition": "Applications Denied", 
                    "count": 1, 
                    "value": 93
                }, 
                {
                    "disposition": "Applications Withdrawn", 
                    "count": 0, 
                    "value": 0
                }, 
                {
                    "disposition": "Files Closed For Incompleteness", 
                    "count": 0, 
                    "value": 0
                }
            ]
        }, 
        {
            "income": "100-119% of MSA/MD median", 
            "dispositions": [
                {
                    "disposition": "Applications Received", 
                    "count": 2, 
                    "value": 156
                }, 
                {
                    "disposition": "Loans Originated", 
                    "count": 1, 
                    "value": 106
                }, 
                {
                    "disposition": "Apps. Approved But Not Accepted", 
                    "count": 0, 
                    "value": 0
                }, 
                {
                    "disposition": "Applications Denied", 
                    "count": 0, 
                    "value": 0
                }, 
                {
                    "disposition": "Applications Withdrawn", 
                    "count": 1, 
                    "value": 50
                }, 
                {
                    "disposition": "Files Closed For Incompleteness", 
                    "count": 0, 
                    "value": 0
                }
            ]
        }, 
        {
            "income": "120% or more of MSA/MD median", 
            "dispositions": [
                {
                    "disposition": "Applications Received", 
                    "count": 13, 
                    "value": 1835
                }, 
                {
                    "disposition": "Loans Originated", 
                    "count": 11, 
                    "value": 1698
                }, 
                {
                    "disposition": "Apps. Approved But Not Accepted", 
                    "count": 0, 
                    "value": 0
                }, 
                {
                    "disposition": "Applications Denied", 
                    "count": 2, 
                    "value": 137
                }, 
                {
                    "disposition": "Applications Withdrawn", 
                    "count": 0, 
                    "value": 0
                }, 
                {
                    "disposition": "Files Closed For Incompleteness", 
                    "count": 0, 
                    "value": 0
                }
            ]
        }, 
        {
            "income": "Income Not Available", 
            "dispositions": [
                {
                    "disposition": "Applications Received", 
                    "count": 1, 
                    "value": 225
                }, 
                {
                    "disposition": "Loans Originated", 
                    "count": 1, 
                    "value": 225
                }, 
                {
                    "disposition": "Apps. Approved But Not Accepted", 
                    "count": 0, 
                    "value": 0
                }, 
                {
                    "disposition": "Applications Denied", 
                    "count": 0, 
                    "value": 0
                }, 
                {
                    "disposition": "Applications Withdrawn", 
                    "count": 0, 
                    "value": 0
                }, 
                {
                    "disposition": "Files Closed For Incompleteness", 
                    "count": 0, 
                    "value": 0
                }
            ]
        }
    ], 
    "total": [
        {
            "disposition": "Applications Received", 
            "count": 22, 
            "value": 2542
        }, 
        {
            "disposition": "Loans Originated", 
            "count": 14, 
            "value": 2083
        }, 
        {
            "disposition": "Apps. Approved But Not Accepted", 
            "count": 0, 
            "value": 0
        }, 
        {
            "disposition": "Applications Denied", 
            "count": 6, 
            "value": 354
        }, 
        {
            "disposition": "Applications Withdrawn", 
            "count": 2, 
            "value": 105
        }, 
        {
            "disposition": "Files Closed For Incompleteness", 
            "count": 0, 
            "value": 0
        }
    ]
}